MANIFEST.in
README.rst
setup.py
bin/compose_plantuml
compose_plantuml/__init__.py
compose_plantuml.egg-info/PKG-INFO
compose_plantuml.egg-info/SOURCES.txt
compose_plantuml.egg-info/dependency_links.txt
compose_plantuml.egg-info/not-zip-safe
compose_plantuml.egg-info/top_level.txt
features/a.feature
features/boundaries.feature
features/link_graph.feature