Metadata-Version: 1.1
Name: compose-plantuml
Version: 0.2.1
Summary: converts docker-compose into plantuml
Home-page: http://github.com/funkwerk/compose_plantuml
Author: Stefan Rohe
Author-email: UNKNOWN
License: MIT
Keywords: docker-compose plantuml docker yml
Platform: UNKNOWN
Classifier: License :: OSI Approved :: MIT License
Classifier: Programming Language :: Python :: 3
Classifier: Topic :: Software Development
Classifier: Environment :: Console
Classifier: Operating System :: OS Independent
